storeweights/__init__.py
storeweights/mount_drive.py
storeweights/weights.py
storeweights-1.0.2.dist-info/LICENSE
storeweights-1.0.2.dist-info/METADATA
storeweights-1.0.2.dist-info/WHEEL
storeweights-1.0.2.dist-info/top_level.txt
storeweights-1.0.2.dist-info/RECORD
