Metadata-Version: 2.1
Name: storeweights
Version: 1.0.2
Summary: Storing PyTorch checkpoints in efficient way
Home-page: https://github.com/apthagowda97/storeweights
Author: Aptha K S
Author-email: iamuraptha@gmail.com
License: MIT
Platform: UNKNOWN
Classifier: Intended Audience :: Science/Research
Classifier: License :: OSI Approved :: MIT License
Classifier: Programming Language :: Python :: 3.6
Classifier: Topic :: Scientific/Engineering :: Artificial Intelligence
Requires-Python: >=3.6
Requires-Dist: numpy
